manim_fontawesome/__init__.py
manim_fontawesome/__init__.pyi
manim_fontawesome/font-awesome/LICENSE.txt
manim_fontawesome/font-awesome/svgs/brands/42-group.svg
manim_fontawesome/font-awesome/svgs/brands/500px.svg
manim_fontawesome/font-awesome/svgs/brands/accessible-icon.svg
manim_fontawesome/font-awesome/svgs/brands/accusoft.svg
manim_fontawesome/font-awesome/svgs/brands/adn.svg
manim_fontawesome/font-awesome/svgs/brands/adversal.svg
manim_fontawesome/font-awesome/svgs/brands/affiliatetheme.svg
manim_fontawesome/font-awesome/svgs/brands/airbnb.svg
manim_fontawesome/font-awesome/svgs/brands/algolia.svg
manim_fontawesome/font-awesome/svgs/brands/alipay.svg
manim_fontawesome/font-awesome/svgs/brands/amazon-pay.svg
manim_fontawesome/font-awesome/svgs/brands/amazon.svg
manim_fontawesome/font-awesome/svgs/brands/amilia.svg
manim_fontawesome/font-awesome/svgs/brands/android.svg
manim_fontawesome/font-awesome/svgs/brands/angellist.svg
manim_fontawesome/font-awesome/svgs/brands/angrycreative.svg
manim_fontawesome/font-awesome/svgs/brands/angular.svg
manim_fontawesome/font-awesome/svgs/brands/app-store-ios.svg
manim_fontawesome/font-awesome/svgs/brands/app-store.svg
manim_fontawesome/font-awesome/svgs/brands/apper.svg
manim_fontawesome/font-awesome/svgs/brands/apple-pay.svg
manim_fontawesome/font-awesome/svgs/brands/apple.svg
manim_fontawesome/font-awesome/svgs/brands/artstation.svg
manim_fontawesome/font-awesome/svgs/brands/asymmetrik.svg
manim_fontawesome/font-awesome/svgs/brands/atlassian.svg
manim_fontawesome/font-awesome/svgs/brands/audible.svg
manim_fontawesome/font-awesome/svgs/brands/autoprefixer.svg
manim_fontawesome/font-awesome/svgs/brands/avianex.svg
manim_fontawesome/font-awesome/svgs/brands/aviato.svg
manim_fontawesome/font-awesome/svgs/brands/aws.svg
manim_fontawesome/font-awesome/svgs/brands/bandcamp.svg
manim_fontawesome/font-awesome/svgs/brands/battle-net.svg
manim_fontawesome/font-awesome/svgs/brands/behance-square.svg
manim_fontawesome-6.0.0.dist-info/entry_points.txt
manim_fontawesome-6.0.0.dist-info/LICENSE.txt
manim_fontawesome-6.0.0.dist-info/WHEEL
manim_fontawesome-6.0.0.dist-info/METADATA
manim_fontawesome-6.0.0.dist-info/RECORD
